pyproject.toml
setup.cfg
setup.py
src/iso_timer/__init__.py
src/iso_timer.egg-info/PKG-INFO
src/iso_timer.egg-info/SOURCES.txt
src/iso_timer.egg-info/dependency_links.txt
src/iso_timer.egg-info/requires.txt
src/iso_timer.egg-info/top_level.txt
src/iso_timer/common/__init__.py
src/iso_timer/common/format.py