Metadata-Version: 2.1
Name: iso-timer
Version: 0.1
Summary: global use
Author: starlight
Author-email: mylifcc@gmail.com
